tsmpy/__init__.py
tsmpy/compaction.py
tsmpy/flownet.py
tsmpy/orthogonalization.py
tsmpy/planarization.py
tsmpy/tsm.py
tsmpy/utils.py
tsmpy/dcel/__init__.py
tsmpy/dcel/dcel.py
tsmpy/dcel/face.py
tsmpy/dcel/halfedge.py
tsmpy/dcel/vertex.py
tsmpy/tsm/__init__.py
tsmpy/tsm/compaction.py
tsmpy/tsm/flownet.py
tsmpy/tsm/orthogonalization.py
tsmpy/tsm/planarization.py
tsmpy/tsm/tsm.py
tsmpy/tsm/utils.py
tsmpy-0.9.3.dist-info/LICENSE
tsmpy-0.9.3.dist-info/METADATA
tsmpy-0.9.3.dist-info/WHEEL
tsmpy-0.9.3.dist-info/top_level.txt
tsmpy-0.9.3.dist-info/RECORD
