Metadata-Version: 2.1
Name: tsmpy
Version: 0.9.3
Summary: An orthogonal layout algorithm, using TSM approach
Home-page: https://github.com/uknfire/tsmpy
Author: uknfire
Author-email: uknfire@gmail.com
License: MIT
Project-URL: Source, https://github.com/uknfire/tsmpy
Keywords: Graph Drawing,orthogonal,layout,graph
Platform: UNKNOWN
Requires-Python: >=3.6
License-File: LICENSE
Requires-Dist: networkx
Requires-Dist: pulp
